LCoder/__init__.py
LCoder/main.py
LCoder-0.11.dist-info/METADATA
LCoder-0.11.dist-info/WHEEL
LCoder-0.11.dist-info/top_level.txt
LCoder-0.11.dist-info/RECORD
