Metadata-Version: 2.1
Name: LCoder
Version: 0.11
